spineps/.vscode/settings.json
spineps/__init__.py
spineps/architectures/__init__.py
spineps/architectures/pl_densenet.py
spineps/architectures/pl_unet.py
spineps/architectures/read_labels.py
spineps/architectures/unet3D.py
spineps/entrypoint.py
spineps/example/figures/example_semantic.png
spineps/example/figures/pipeline_processflow.png
spineps/example/get_gpu.py
spineps/example/helper_parallel.py
spineps/example/template_roll_out.py
spineps/get_models.py
spineps/lab_model.py
spineps/phase_instance.py
spineps/phase_labeling.py
spineps/phase_post.py
spineps/phase_pre.py
spineps/phase_semantic.py
spineps/seg_enums.py
spineps/seg_model.py
spineps/seg_pipeline.py
spineps/seg_run.py
spineps/seg_utils.py
spineps/utils/__init__.py
spineps/utils/auto_download.py
spineps/utils/citation_reminder.py
spineps/utils/compat.py
spineps/utils/data_iterators.py
spineps/utils/default_preprocessor.py
spineps/utils/export_prediction.py
spineps/utils/filepaths.py
spineps/utils/find_min_cost_path.py
spineps/utils/generate_disc_labels.py
spineps/utils/get_network_from_plans.py
spineps/utils/image.py
spineps/utils/inference_api.py
spineps/utils/plans_handler.py
spineps/utils/predictor.py
spineps/utils/proc_functions.py
spineps/utils/seg_modelconfig.py
spineps/utils/sliding_window_prediction.py
spineps-1.4.2.dist-info/METADATA
spineps-1.4.2.dist-info/WHEEL
spineps-1.4.2.dist-info/entry_points.txt
spineps-1.4.2.dist-info/licenses/LICENSE
spineps-1.4.2.dist-info/RECORD
