Metadata-Version: 2.4
Name: SPINEPS
Version: 1.4.2
Summary: Framework for out-of-the box whole spine MRI segmentation.
License: Apache License Version 2.0, January 2004
License-File: LICENSE
Author: Hendrik Möller
Author-email: hendrik.moeller@tum.de
Requires-Python: >=3.9,<4.0
Classifier: License :: Other/Proprietary License
Classifier: Programming Language :: Python :: 3
Classifier: Programming Language :: Python :: 3.9
Classifier: Programming Language :: Python :: 3.10
Classifier: Programming Language :: Python :: 3.11
Classifier: Programming Language :: Python :: 3.12
Classifier: Programming Language :: Python :: 3.13
Classifier: Programming Language :: Python :: 3.14
Requires-Dist: SciPy (>=1.11.2,<2.0.0)
Requires-Dist: TPTBox (>=0.4.0,<0.5.0)
Requires-Dist: TypeSaveArgParse (>=1.0.1,<2.0.0)
Requires-Dist: acvl-utils (==0.2)
Requires-Dist: antspyx (==0.4.2)
Requires-Dist: connected-components-3d (>=3.12.3,<4.0.0)
Requires-Dist: einops (>=0.6.1,<0.7.0)
Requires-Dist: fill-voids (>=2.0.5,<3.0.0)
Requires-Dist: monai (>=1.3.0,<2.0.0)
Requires-Dist: nibabel (>=5.1.0,<6.0.0)
Requires-Dist: nnunetv2 (==2.4.2)
Requires-Dist: numpy (>=1.25.2,<2.0.0)
Requires-Dist: pathlib (>=1.0.1,<2.0.0)
Requires-Dist: pytorch-lightning (>=2.0.8,<3.0.0)
Requires-Dist: rich (>=13.6.0,<14.0.0)
Requires-Dist: torchmetrics (>=1.1.2,<2.0.0)
Requires-Dist: tqdm (>=4.66.1,<5.0.0)
Project-URL: Homepage, https://github.com/Hendrik-code/spineps
Project-URL: Repository, https://github.com/Hendrik-code/spineps
